.DS_Store
etm/__init__.py
etm/__main__ [conflicted].py
etm/__main__.py
etm/__version__ [conflicted].py
etm/__version__.py
etm/data.py
etm/ical.py
etm/make_examples.py
etm/model.py
etm/options.py
etm/report.py
etm/view.py
etm_dgraham-5.1.19.dist-info/METADATA
etm_dgraham-5.1.19.dist-info/PKG-INFO [conflicted]
etm_dgraham-5.1.19.dist-info/SOURCES [conflicted].txt
etm_dgraham-5.1.19.dist-info/WHEEL
etm_dgraham-5.1.19.dist-info/entry_points.txt
etm_dgraham-5.1.19.dist-info/requires [conflicted].txt
etm_dgraham-5.1.19.dist-info/top_level [conflicted].txt
etm_dgraham-5.1.19.dist-info/top_level.txt
etm_dgraham-5.1.19.dist-info/RECORD
