Metadata-Version: 2.1
Name: etm-dgraham
Version: 5.1.19
Summary: event and task manager
Home-page: https://dagraham.github.io/etm-dgraham/
Author: Daniel A Graham
Author-email: dnlgrhm@gmail.com
License: GPL
Classifier: Development Status :: 5 - Production/Stable
Classifier: Environment :: Console
Classifier: Intended Audience :: End Users/Desktop
Classifier: License :: OSI Approved :: GNU General Public License (GPL)
Classifier: Programming Language :: Python
Classifier: Programming Language :: Python :: 3.7
Classifier: Programming Language :: Python :: 3.8
Classifier: Programming Language :: Python :: Implementation :: CPython
Classifier: Programming Language :: Python :: Implementation :: PyPy
Classifier: Topic :: Office/Business
Classifier: Topic :: Office/Business :: News/Diary
Classifier: Topic :: Office/Business :: Scheduling
Requires-Python: >=3.7.3, <=3.11.6
Requires-Dist: icalendar >=4.0.3
Requires-Dist: Jinja2 >=2.10
Requires-Dist: lorem >=0.1.1
Requires-Dist: MarkupSafe >=1.1.0
Requires-Dist: pendulum >=2.0.4
Requires-Dist: prompt-toolkit >=3.0.2
Requires-Dist: Pygments >=2.5.2
Requires-Dist: pyperclip >=1.7.0
Requires-Dist: python-dateutil >=2.7.3
Requires-Dist: pytz >=2018.9
Requires-Dist: pytzdata >=2018.9
Requires-Dist: ruamel.yaml >=0.15.88
Requires-Dist: requests >=2.25.1
Requires-Dist: six >=1.11.0
Requires-Dist: style >=1.1.6
Requires-Dist: tinydb >=3.12.2
Requires-Dist: tinydb-serialization >=1.0.4
Requires-Dist: tinydb-smartcache >=1.0.2
Requires-Dist: tzlocal >=1.5.1
Requires-Dist: wcwidth >=0.1.7
Requires-Dist: packaging >=22.0
